wagalytics/__init__.py
wagalytics/urls.py
wagalytics/views.py
wagalytics/wagtail_hooks.py
wagalytics/static/wagalytics/.gitkeep
wagalytics/static/wagalytics/bundle.js.map
wagalytics/static/wagalytics/vendors.bundle.js
wagalytics/static/wagalytics/wagalytics.bundle.js
wagalytics/templates/wagalytics/dashboard.html
wagalytics-1.0.dist-info/LICENSE
wagalytics-1.0.dist-info/METADATA
wagalytics-1.0.dist-info/WHEEL
wagalytics-1.0.dist-info/top_level.txt
wagalytics-1.0.dist-info/RECORD
